omemo/__init__.py
omemo/backend.py
omemo/bundle.py
omemo/cli.py
omemo/identity_key_pair.py
omemo/message.py
omemo/py.typed
omemo/session.py
omemo/session_manager.py
omemo/storage.py
omemo/types.py
omemo/version.py
omemo-2.1.0.dist-info/licenses/LICENSE
omemo-2.1.0.dist-info/METADATA
omemo-2.1.0.dist-info/WHEEL
omemo-2.1.0.dist-info/top_level.txt
omemo-2.1.0.dist-info/RECORD
