Metadata-Version: 2.4
Name: OMEMO
Version: 2.1.0
Summary: A Python implementation of the OMEMO Multi-End Message and Object Encryption protocol.
Author-email: "Tim Henkes (Syndace)" <me@syndace.dev>
Maintainer-email: "Tim Henkes (Syndace)" <me@syndace.dev>
License-Expression: MIT
Project-URL: Documentation, https://py-omemo.readthedocs.io/
Project-URL: Repository, https://github.com/Syndace/python-omemo
Project-URL: Issues, https://github.com/Syndace/python-omemo/issues
Project-URL: Changelog, https://github.com/Syndace/python-omemo/blob/main/CHANGELOG.md
Classifier: Development Status :: 5 - Production/Stable
Classifier: Programming Language :: Python :: 3
Classifier: Programming Language :: Python :: 3 :: Only
Classifier: Programming Language :: Python :: 3.10
Classifier: Programming Language :: Python :: 3.11
Classifier: Programming Language :: Python :: 3.12
Classifier: Programming Language :: Python :: 3.13
Classifier: Programming Language :: Python :: 3.14
Classifier: Programming Language :: Python :: Implementation :: CPython
Classifier: Programming Language :: Python :: Implementation :: PyPy
Classifier: Intended Audience :: Developers
Classifier: Topic :: Communications :: Chat
Classifier: Topic :: Security :: Cryptography
Requires-Python: >=3.10
License-File: LICENSE
Requires-Dist: XEdDSA<2,>=1.0.0
Requires-Dist: typing-extensions>=4.3.0
Provides-Extra: cli
Requires-Dist: prettytable<4,>=3.16.0; extra == "cli"
Provides-Extra: docs
Requires-Dist: sphinx; extra == "docs"
Requires-Dist: sphinx-rtd-theme; extra == "docs"
Requires-Dist: sphinx-autodoc-typehints; extra == "docs"
Provides-Extra: test
Requires-Dist: pytest; extra == "test"
Requires-Dist: pytest-asyncio; extra == "test"
Requires-Dist: pytest-cov; extra == "test"
Requires-Dist: twisted; extra == "test"
Requires-Dist: twomemo[xml]; extra == "test"
Requires-Dist: oldmemo[xml]; extra == "test"
Provides-Extra: lint
Requires-Dist: mypy; extra == "lint"
Requires-Dist: pylint; extra == "lint"
Requires-Dist: flake8; extra == "lint"
Requires-Dist: flake8-pyproject; extra == "lint"
Provides-Extra: dev
Requires-Dist: omemo[cli,docs,lint,test]; extra == "dev"
Dynamic: license-file
